{
  "platform": "ebay",
  "product_data": {
    "title": "Dell Latitude 5420 Laptop 14\" Windows 11 Intel Core i5 4.4GHz 8GB RAM 128GB SSDGood - Refurbished·Dell$211.18or Best Offer+$239.86 deliveryLocated in United StateseBay RefurbishedderosnopS",
    "price": 211.18,
    "original_price": 211.18,
    "currency": "USD",
    "url": "https://www.ebay.com/itm/254582474636?_skw=laptop&itmmeta=01K2FTBCFQARA1BT14K522Z10G&hash=item3b464c478c:g:fjgAAOSw7XdoIwd3&itmprp=enc%3AAQAKAAAA4FkggFvd1GGDu0w3yXCmi1d2u%2BTJbpfFCtqBvCGWMvOfhriQUmRujCz90gGpxi3qxZPzxq5Ol%2B2QqfHml9GCCwMpXNupySw449DbZ7foN3YNxJbKtVgPp%2FOFPEZvjEtJWj%2FFy%2Bp2sUhRs%2FnUWUWfdJq7ueWAZwaI0pHkiz0bRZWjpaipqKhatI%2FGJbdgS71kyQ371mUCROgdQE9y58SVeoCYUrDRDpJPoBYXVn5aBiBbA1ocwl9op63hwua29dxsw2HdS2ZyAygWiY39JOK5nRaJxImeyN5FLLdkzM3amJO%2B%7Ctkp%3ABFBM_set-pNm",
    "image_url": "",
    "condition": "refurbished",
    "sale_type": "fixed_price",
    "time_left": "",
    "bid_count": 0,
    "seller": {
      "name": "",
      "feedback": "",
      "location": ""
    },
    "shipping": {
      "cost": "+$239.86 delivery",
      "location": "Located in United States"
    },
    "item_id": "254582474636",
    "platform": "ebay",
    "search_term": "laptop",
    "condition_filter": "all"
  },
  "scraped_at": "2025-08-12T20:58:42.003781"
}